MANIFEST.in
README.txt
plonetheme.inbusiness-configure.zcml
setup.cfg
setup.py
Extensions/install.py
docs/HISTORY.txt
docs/INSTALL.txt
docs/LICENSE.GPL
docs/LICENSE.txt
plonetheme/__init__.py
plonetheme.inbusiness.egg-info/PKG-INFO
plonetheme.inbusiness.egg-info/SOURCES.txt
plonetheme.inbusiness.egg-info/dependency_links.txt
plonetheme.inbusiness.egg-info/entry_points.txt
plonetheme.inbusiness.egg-info/namespace_packages.txt
plonetheme.inbusiness.egg-info/not-zip-safe
plonetheme.inbusiness.egg-info/requires.txt
plonetheme.inbusiness.egg-info/top_level.txt
plonetheme/inbusiness/__init__.py
plonetheme/inbusiness/configure.zcml
plonetheme/inbusiness/profiles.zcml
plonetheme/inbusiness/setuphandlers.py
plonetheme/inbusiness/skins.zcml
plonetheme/inbusiness/tests.py
plonetheme/inbusiness/version.txt
plonetheme/inbusiness/browser/__init__.py
plonetheme/inbusiness/browser/configure.zcml
plonetheme/inbusiness/browser/interfaces.py
plonetheme/inbusiness/browser/logo.pt
plonetheme/inbusiness/browser/portal_title_viewlet.pt
plonetheme/inbusiness/browser/viewlet.pt
plonetheme/inbusiness/browser/viewlets.py
plonetheme/inbusiness/browser/images/README.txt
plonetheme/inbusiness/browser/stylesheets/README.txt
plonetheme/inbusiness/browser/stylesheets/main.css
plonetheme/inbusiness/profiles/default/cssregistry.xml
plonetheme/inbusiness/profiles/default/import_steps.xml
plonetheme/inbusiness/profiles/default/jsregistry.xml
plonetheme/inbusiness/profiles/default/metadata.xml
plonetheme/inbusiness/profiles/default/plonetheme.inbusiness_various.txt
plonetheme/inbusiness/profiles/default/skins.xml
plonetheme/inbusiness/profiles/default/viewlets.xml
plonetheme/inbusiness/profiles/uninstall/skins.xml
plonetheme/inbusiness/profiles/uninstall/viewlets.xml
plonetheme/inbusiness/skins/plonetheme_inbusiness_custom_images/CONTENT.txt
plonetheme/inbusiness/skins/plonetheme_inbusiness_custom_images/b.gif
plonetheme/inbusiness/skins/plonetheme_inbusiness_custom_images/corner.gif
plonetheme/inbusiness/skins/plonetheme_inbusiness_custom_images/corner2.gif
plonetheme/inbusiness/skins/plonetheme_inbusiness_custom_images/corner3.gif
plonetheme/inbusiness/skins/plonetheme_inbusiness_custom_images/corner4.gif
plonetheme/inbusiness/skins/plonetheme_inbusiness_custom_images/www.jpg
plonetheme/inbusiness/skins/plonetheme_inbusiness_custom_templates/CONTENT.txt
