Metadata-Version: 1.0
Name: plonetheme.inbusiness
Version: 1.0
Summary: An installable theme for Plone 3.0
Home-page: http://svn.plone.org/svn/collective/plonetheme.inbusiness/
Author: Scott Alan Greiff
Author-email: scott@greiff.org
License: GPL
Keywords: web zope plone theme
Platform: UNKNOWN
Classifier: Framework :: Plone
Classifier: Programming Language :: Python
Classifier: Topic :: Software Development :: Libraries :: Python Modules
